pyenzymekinetics/__init__.py
pyenzymekinetics/calibrator/__init__.py
pyenzymekinetics/calibrator/calibrationmodel.py
pyenzymekinetics/calibrator/standardcurve.py
pyenzymekinetics/calibrator/utility.py
pyenzymekinetics/parameterestimator/__init__.py
pyenzymekinetics/parameterestimator/enzymekinetics.py
pyenzymekinetics/parameterestimator/models.py
pyenzymekinetics/utility/__init__.py
pyenzymekinetics/utility/initial_parameters.py
pyenzymekinetics/utility/writeenzymeml.py
PyEnzymeKinetics-1.1.6.dist-info/METADATA
PyEnzymeKinetics-1.1.6.dist-info/WHEEL
PyEnzymeKinetics-1.1.6.dist-info/top_level.txt
PyEnzymeKinetics-1.1.6.dist-info/RECORD
