Metadata-Version: 2.1
Name: PyEnzymeKinetics
Version: 1.1.6
Home-page: https://github.com/haeussma/PyEnzymeKinetics
Author: Haeussler, Max
Author-email: max.haeussler@gmail.com
Requires-Dist: lmfit
Requires-Dist: matplotlib
Requires-Dist: scipy
Requires-Dist: numpy
